rongda_mcp_server/__about__.py
rongda_mcp_server/__init__.py
rongda_mcp_server/__main__.py
rongda_mcp_server/api.py
rongda_mcp_server/login.py
rongda_mcp_server/models.py
rongda_mcp_server/py.typed
rongda_mcp_server/server.py
rongda_mcp_server-0.3.2.dist-info/METADATA
rongda_mcp_server-0.3.2.dist-info/WHEEL
rongda_mcp_server-0.3.2.dist-info/entry_points.txt
rongda_mcp_server-0.3.2.dist-info/licenses/LICENSE
rongda_mcp_server-0.3.2.dist-info/RECORD
